ACNH_pixel_color/ACNH_pixel_color.py
ACNH_pixel_color/__init__.py
ACNH_pixel_color/__main__.py
ACNH_pixel_color/res/ACNH_color_palette
ACNH_pixel_color/res/__init__.py
ACNH_pixel_color/res/farben.txt
ACNH_pixel_color-0.2.0.dist-info/LICENSE
ACNH_pixel_color-0.2.0.dist-info/METADATA
ACNH_pixel_color-0.2.0.dist-info/WHEEL
ACNH_pixel_color-0.2.0.dist-info/top_level.txt
ACNH_pixel_color-0.2.0.dist-info/RECORD
