Metadata-Version: 2.1
Name: ACNH-pixel-color
Version: 0.2.0
Summary: A program to associate IDs with h/v/b values for color matching in ACNH
Home-page: https://github.com/burnish3d/ACNH_pixel_color
Author: Zachary Chandler
Author-email: zachary.c.me@gmail.com
License: MIT
Platform: UNKNOWN
Classifier: Programming Language :: Python :: 3.10
Classifier: License :: OSI Approved :: MIT License
License-File: LICENSE
